prstat/__init__.py
prstat/prstat.py
prstat-1.1.1.dist-info/LICENSE
prstat-1.1.1.dist-info/METADATA
prstat-1.1.1.dist-info/WHEEL
prstat-1.1.1.dist-info/top_level.txt
prstat-1.1.1.dist-info/RECORD
