Metadata-Version: 2.1
Name: prstat
Version: 1.1.1
Summary: tools for pnu probabilities and statistics class
Home-page: https://github.com/karinysis/prstat
Author: youngjae lee
Author-email: leeyoungjae@pusan.ac.kr
License: MIT
License-File: LICENSE
Requires-Dist: sympy
Requires-Dist: numpy
